{
  "content": {
    "extra": [
      {
        "bold": true,
        "color": "black",
        "extra": [
          "\n"
        ],
        "font": "minecraft:uniform",
        "translate": "book.enerjolt.page.duration_upgrades.1"
      },
      {
        "color": "black",
        "font": "minecraft:uniform",
        "italic": true,
        "translate": "book.enerjolt.page.duration_upgrades.2"
      }
    ],
    "text": ""
  },
  "image": [
    "enerjolt:textures/item/duration_upgrade_module_1.png",
    "enerjolt:textures/item/duration_upgrade_module_2.png",
    "enerjolt:textures/item/duration_upgrade_module_3.png",
    "enerjolt:textures/item/duration_upgrade_module_4.png",
    "enerjolt:textures/item/duration_upgrade_module_5.png",
    "enerjolt:textures/item/duration_upgrade_module_6.png"
  ]
}